feishu_docx/__init__.py
feishu_docx/auth/__init__.py
feishu_docx/auth/oauth.py
feishu_docx/auth/templates.py
feishu_docx/cli/__init__.py
feishu_docx/cli/main.py
feishu_docx/core/__init__.py
feishu_docx/core/exporter.py
feishu_docx/core/sdk.py
feishu_docx/core/parsers/__init__.py
feishu_docx/core/parsers/bitable.py
feishu_docx/core/parsers/document.py
feishu_docx/core/parsers/sheet.py
feishu_docx/schema/__init__.py
feishu_docx/schema/code_style.py
feishu_docx/schema/models.py
feishu_docx/tui/CLAUDE.md
feishu_docx/tui/__init__.py
feishu_docx/tui/app.py
feishu_docx/tui/constants.py
feishu_docx/tui/styles.py
feishu_docx/utils/__init__.py
feishu_docx/utils/config.py
feishu_docx/utils/progress.py
feishu_docx/utils/render_table.py
feishu_docx-0.1.4.dist-info/METADATA
feishu_docx-0.1.4.dist-info/WHEEL
feishu_docx-0.1.4.dist-info/entry_points.txt
feishu_docx-0.1.4.dist-info/licenses/LICENSE
feishu_docx-0.1.4.dist-info/RECORD
