Metadata-Version: 2.4
Name: feishu-docx
Version: 0.1.4
Summary: Export Feishu/Lark cloud documents to Markdown
Project-URL: Homepage, https://github.com/leemysw/feishu-docx
Project-URL: Repository, https://github.com/leemysw/feishu-docx.git
Project-URL: Documentation, https://github.com/leemysw/feishu-docx#readme
Author: leemysw
License-Expression: MIT
License-File: LICENSE
Keywords: document,export,feishu,lark,markdown,飞书
Classifier: Development Status :: 4 - Beta
Classifier: Environment :: Console
Classifier: Intended Audience :: Developers
Classifier: License :: OSI Approved :: MIT License
Classifier: Programming Language :: Python :: 3
Classifier: Programming Language :: Python :: 3.11
Classifier: Programming Language :: Python :: 3.12
Classifier: Topic :: Text Processing :: Markup :: Markdown
Classifier: Topic :: Utilities
Requires-Python: >=3.11
Requires-Dist: httpx>=0.27.0
Requires-Dist: lark-oapi>=1.4.24
Requires-Dist: pydantic>=2.0
Requires-Dist: rich>=13.0
Requires-Dist: textual>=0.85.0
Requires-Dist: typer[all]>=0.12.0
Provides-Extra: dev
Requires-Dist: mypy>=1.10; extra == 'dev'
Requires-Dist: pytest>=8.0; extra == 'dev'
Requires-Dist: ruff>=0.6; extra == 'dev'
